py3adb/__init__.py
py3adb/adb.py
py3adb-3.0.4.dist-info/LICENSE
py3adb-3.0.4.dist-info/METADATA
py3adb-3.0.4.dist-info/WHEEL
py3adb-3.0.4.dist-info/top_level.txt
py3adb-3.0.4.dist-info/RECORD
